a_jupyterlab_session/__init__.py
a_jupyterlab_session/_version.py
a_jupyterlab_session-0.2.0.data/data/share/jupyter/labextensions/a-jupyterlab-session/package.json
a_jupyterlab_session-0.2.0.data/data/share/jupyter/labextensions/a-jupyterlab-session/static/329.fcf07adac30b3d987585.js
a_jupyterlab_session-0.2.0.data/data/share/jupyter/labextensions/a-jupyterlab-session/static/509.9714ce34b3573ea88ab6.js
a_jupyterlab_session-0.2.0.data/data/share/jupyter/labextensions/a-jupyterlab-session/static/728.a84357ed32532b9c330f.js
a_jupyterlab_session-0.2.0.data/data/share/jupyter/labextensions/a-jupyterlab-session/static/remoteEntry.8cbae3614c71931bb769.js
a_jupyterlab_session-0.2.0.data/data/share/jupyter/labextensions/a-jupyterlab-session/static/style.js
a_jupyterlab_session-0.2.0.data/data/share/jupyter/labextensions/a-jupyterlab-session/static/third-party-licenses.json
a_jupyterlab_session-0.2.0.data/data/share/jupyter/labextensions/a-jupyterlab-session/install.json
a_jupyterlab_session-0.2.0.dist-info/METADATA
a_jupyterlab_session-0.2.0.dist-info/WHEEL
a_jupyterlab_session-0.2.0.dist-info/licenses/LICENSE
a_jupyterlab_session-0.2.0.dist-info/RECORD
