Metadata-Version: 2.4
Name: a-jupyterlab-session
Version: 0.2.0
Dynamic: Keywords
Summary: A JupyterLab extension.
Project-URL: Homepage, https://github.com/juntyr/a-jupyterlab-session
Project-URL: Bug Tracker, https://github.com/juntyr/a-jupyterlab-session/issues
Project-URL: Repository, https://github.com/juntyr/a-jupyterlab-session.git
Author-email: Juniper Tyree <juniper.tyree@helsinki.fi>
License: BSD 3-Clause License
License-File: LICENSE
Classifier: Framework :: Jupyter
Classifier: Framework :: Jupyter :: JupyterLab
Classifier: Framework :: Jupyter :: JupyterLab :: 4
Classifier: Framework :: Jupyter :: JupyterLab :: Extensions
Classifier: Framework :: Jupyter :: JupyterLab :: Extensions :: Prebuilt
Classifier: License :: OSI Approved :: BSD License
Classifier: Programming Language :: Python
Classifier: Programming Language :: Python :: 3
Classifier: Programming Language :: Python :: 3.8
Classifier: Programming Language :: Python :: 3.9
Classifier: Programming Language :: Python :: 3.10
Classifier: Programming Language :: Python :: 3.11
Classifier: Programming Language :: Python :: 3.12
Requires-Python: >=3.8
